obscure_stats/__init__.py
obscure_stats/association/__init__.py
obscure_stats/association/association.py
obscure_stats/central_tendency/__init__.py
obscure_stats/central_tendency/central_tendency.py
obscure_stats/dispersion/__init__.py
obscure_stats/dispersion/dispersion.py
obscure_stats/kurtosis/__init__.py
obscure_stats/kurtosis/kurtosis.py
obscure_stats/skewness/__init__.py
obscure_stats/skewness/skewness.py
obscure_stats/variation/__init__.py
obscure_stats/variation/variation.py
obscure_stats-0.5.0.dist-info/LICENSE.txt
obscure_stats-0.5.0.dist-info/METADATA
obscure_stats-0.5.0.dist-info/WHEEL
obscure_stats-0.5.0.dist-info/RECORD
